{
	"name": "Wima",
	"version": "1.25.0",
	"author": [
		"Gabriel Wicke",
		"WikiMANNia",
		"..."
	],
	"url": "https://github.com/WikiMANNia/MediaWiki-Skins-with-Advertisements/releases/tag/1.25.0-w",
	"descriptionmsg": "wima-desc",
	"namemsg": "skinname-wima",
	"license-name": "GPL-2.0+",
	"type": "skin",
	"ValidSkinNames": {
		"wima": "Wima"
	},
	"MessagesDirs": {
		"Wima": [
			"i18n"
		]
	},
	"ResourceModules": {
		"skins.monobook.styles": {
			"styles": {
				"main.css": {
					"media": "screen"
				}
			}
		}
	},
	"ResourceFileModulePaths": {
		"localBasePath": "",
		"remoteSkinPath": "Wima"
	},
	"AutoloadClasses": {
		"SkinWima": "includes/SkinWima.php",
		"WimaTemplate": "includes/WimaTemplate.php"
	}
}
